mindbank_poc/__init__.py
mindbank_poc/api/__init__.py
mindbank_poc/api/main.py
mindbank_poc/api/schemas.py
mindbank_poc/api/backends/__init__.py
mindbank_poc/api/backends/jsonl_backend.py
mindbank_poc/api/normalizers/__init__.py
mindbank_poc/api/normalizers/config.py
mindbank_poc/api/normalizers/manager.py
mindbank_poc/api/normalizers/queue_service.py
mindbank_poc/api/routers/__init__.py
mindbank_poc/api/routers/access_tokens.py
mindbank_poc/api/routers/agent_chat.py
mindbank_poc/api/routers/archetypes.py
mindbank_poc/api/routers/connectors.py
mindbank_poc/api/routers/fingerprint_tokens.py
mindbank_poc/api/routers/fsm_sync_router.py
mindbank_poc/api/routers/ingest.py
mindbank_poc/api/routers/integration_keys.py
mindbank_poc/api/routers/onboarding.py
mindbank_poc/api/routers/pipeline.py
mindbank_poc/api/routers/processing_providers.py
mindbank_poc/api/routers/retrieval.py
mindbank_poc/api/routers/status.py
mindbank_poc/cli/__init__.py
mindbank_poc/cli/core.py
mindbank_poc/cli/init_storages.py
mindbank_poc/cli/migrate_ids.py
mindbank_poc/cli/normalizer_runner.py
mindbank_poc/cli/segmentation_runner.py
mindbank_poc/cli/telegram_connector.py
mindbank_poc/cli/ingest-runner/__init__.py
mindbank_poc/common/__init__.py
mindbank_poc/common/logging.py
mindbank_poc/connectors/__init__.py
mindbank_poc/connectors/debug/__init__.py
mindbank_poc/connectors/debug/client.py
mindbank_poc/connectors/debug/connector.py
mindbank_poc/connectors/filesystem/__init__.py
mindbank_poc/connectors/filesystem/client.py
mindbank_poc/connectors/filesystem/connector.py
mindbank_poc/connectors/telegram/__init__.py
mindbank_poc/connectors/telegram/buffer.py
mindbank_poc/connectors/telegram/cli_hub_onboarding.py
mindbank_poc/connectors/telegram/client.py
mindbank_poc/connectors/telegram/client_manager.py
mindbank_poc/connectors/telegram/connector.py
mindbank_poc/connectors/telegram/constants.py
mindbank_poc/connectors/telegram/http_retry.py
mindbank_poc/connectors/telegram/main.py
mindbank_poc-0.1.15.dist-info/METADATA
mindbank_poc-0.1.15.dist-info/WHEEL
mindbank_poc-0.1.15.dist-info/entry_points.txt
mindbank_poc-0.1.15.dist-info/top_level.txt
mindbank_poc-0.1.15.dist-info/RECORD
