Metadata-Version: 2.4
Name: mindbank-poc
Version: 0.1.15
Summary: Mindbank PoC: Data ingestion and processing platform
Requires-Python: >=3.12
Requires-Dist: pydantic-settings
Requires-Dist: loguru
Requires-Dist: python-dotenv
Requires-Dist: numpy<2
Requires-Dist: keybert
Requires-Dist: scikit-learn>=1.6.1
Requires-Dist: umap-learn>=0.5.3
Requires-Dist: sentence-transformers>=2.2.2
Requires-Dist: chromadb>=0.4.22
Requires-Dist: psutil>=7.0.0
Requires-Dist: torch==2.2.2
Requires-Dist: fastapi
Requires-Dist: uvicorn[standard]>=0.34.2
Requires-Dist: aiofiles
Requires-Dist: pydantic>=2.0
Requires-Dist: aiohttp>=3.11.18
Requires-Dist: openai>=1.0.0
Requires-Dist: dspy
Requires-Dist: telethon>=1.32.1
Requires-Dist: requests>=2.32.0
Requires-Dist: httpx>=0.25.0
Requires-Dist: dspy>=2.6.24
Provides-Extra: core
Requires-Dist: pydantic-settings; extra == "core"
Requires-Dist: loguru; extra == "core"
Requires-Dist: chromadb>=0.4.22; extra == "core"
Provides-Extra: providers-openai
Requires-Dist: openai>=1.0.0; extra == "providers-openai"
Provides-Extra: connectors-telegram
Requires-Dist: telethon>=1.32.1; extra == "connectors-telegram"
Requires-Dist: pillow>=10.0.0; extra == "connectors-telegram"
Requires-Dist: aiofiles>=23.2.1; extra == "connectors-telegram"
Requires-Dist: httpx>=0.25.0; extra == "connectors-telegram"
Requires-Dist: python-magic>=0.4.27; extra == "connectors-telegram"
Requires-Dist: aiohttp>=3.9.3; extra == "connectors-telegram"
Requires-Dist: pydantic>=2.0; extra == "connectors-telegram"
Requires-Dist: requests>=2.32.0; extra == "connectors-telegram"
Provides-Extra: connectors-filesystem
Requires-Dist: httpx; extra == "connectors-filesystem"
Provides-Extra: connectors-debug
Requires-Dist: httpx; extra == "connectors-debug"
Provides-Extra: cli
Requires-Dist: mindbank-poc[core]; extra == "cli"
Requires-Dist: mindbank-poc[providers-openai]; extra == "cli"
Requires-Dist: mindbank-poc[connectors-telegram]; extra == "cli"
Provides-Extra: api
Requires-Dist: mindbank-poc[core]; extra == "api"
Requires-Dist: mindbank-poc[providers-openai]; extra == "api"
Requires-Dist: fastapi; extra == "api"
Requires-Dist: uvicorn[standard]; extra == "api"
Requires-Dist: aiofiles; extra == "api"
Requires-Dist: pydantic>=2.0; extra == "api"
Requires-Dist: requests; extra == "api"
Provides-Extra: test
Requires-Dist: pytest; extra == "test"
Requires-Dist: pytest-asyncio; extra == "test"
Requires-Dist: httpx; extra == "test"
Requires-Dist: Pillow; extra == "test"
Provides-Extra: all
Requires-Dist: mindbank-poc[core]; extra == "all"
Requires-Dist: mindbank-poc[providers-openai]; extra == "all"
Requires-Dist: mindbank-poc[connectors-telegram]; extra == "all"
Requires-Dist: mindbank-poc[connectors-filesystem]; extra == "all"
Requires-Dist: mindbank-poc[connectors-debug]; extra == "all"
Requires-Dist: mindbank-poc[cli]; extra == "all"
Requires-Dist: mindbank-poc[api]; extra == "all"
Requires-Dist: mindbank-poc[test]; extra == "all"
